pyfreetts/__init__.py
pyfreetts/client.py
pyfreetts/const.py
pyfreetts/tts.py
pyfreetts-0.1.1.dist-info/LICENSE
pyfreetts-0.1.1.dist-info/WHEEL
pyfreetts-0.1.1.dist-info/METADATA
pyfreetts-0.1.1.dist-info/RECORD
