Metadata-Version: 2.1
Name: pyfreetts
Version: 0.1.1
Summary: Convert text to speech with the pretty voices
Home-page: https://github.com/tquangsdh20/mateco
License: MIT
Author: Joseph Quang
Author-email: tquangsdh20@fsob.win
Requires-Python: >=3.6,<4.0
Classifier: Development Status :: 5 - Production/Stable
Classifier: Intended Audience :: Education
Classifier: Intended Audience :: End Users/Desktop
Classifier: License :: OSI Approved :: MIT License
Classifier: Operating System :: OS Independent
Classifier: Programming Language :: Python :: 3
Classifier: Programming Language :: Python :: 3.10
Classifier: Programming Language :: Python :: 3.6
Classifier: Programming Language :: Python :: 3.7
Classifier: Programming Language :: Python :: 3.8
Classifier: Programming Language :: Python :: 3.9
Project-URL: Repository, https://github.com/tquangsdh20/mateco
